Tool.py
wxlib/__init__.py
wxlib/wxlibone.py
wxtestlib-1.0.0.dist-info/METADATA
wxtestlib-1.0.0.dist-info/RECORD
wxtestlib-1.0.0.dist-info/WHEEL
wxtestlib-1.0.0.dist-info/top_level.txt
