Metadata-Version: 2.1
Name: wxtestlib
Version: 1.0.0
Summary: this is test lib
Home-page: https://github.com/hugh
Author: wx
Author-email: hugh_wen@sina.com
License: UNKNOWN
Platform: UNKNOWN
